{
  "@context": "dtmi:dtdl:context;2",
  "@id": "dtmi:gov:venusmotors:analyzingsystemmechanism;5",
  "@type": "Interface",
  "displayName": "Analyzingsystemmechanism",
  "contents": [
    {
      "@type": "Telemetry",
      "name": "brightness",
      "schema": "duration"
    },
    {
      "@type": "Property",
      "name": "brightness1",
      "schema": "long"
    },
    {
      "@type": "Property",
      "name": "temperature",
      "schema": "date"
    },
    {
      "@type": "Property",
      "name": "acceleration",
      "schema": "double"
    },
    {
      "@type": "Property",
      "name": "tiltAngle",
      "schema": "time"
    },
    {
      "@type": "Component",
      "name": "monitoringpackunit",
      "schema": "dtmi:gov:crystalcoms:monitoringpackunit;4",
      "displayName": "monitoringpackunit",
      "description": "monitoringpackunit"
    }
  ]
}