{
  "@context": "dtmi:dtdl:context;2",
  "@id": "dtmi:edu:venusmotors:zenithsensingcomputerlaptop;12",
  "@type": "Interface",
  "displayName": "Zenithsensingcomputerlaptop",
  "contents": [
    {
      "@type": "Telemetry",
      "name": "brightness",
      "schema": "time"
    },
    {
      "@type": "Telemetry",
      "name": "tiltAngle",
      "schema": "dateTime"
    },
    {
      "@type": "Property",
      "name": "intensity",
      "schema": "string"
    },
    {
      "@type": "Property",
      "name": "tiltAngle1",
      "schema": "double"
    },
    {
      "@type": "Property",
      "name": "flowRate",
      "schema": "double"
    },
    {
      "@type": "Property",
      "name": "tiltAngle2",
      "schema": "double"
    },
    {
      "@type": "Property",
      "name": "brightness1",
      "schema": "date"
    },
    {
      "@type": "Property",
      "name": "brightness2",
      "schema": "duration"
    },
    {
      "@type": "Component",
      "name": "zenithsensingcomputerlaptop",
      "schema": "dtmi:org:ghostnite:zenithsensingcomputerlaptop;3",
      "displayName": "zenithsensingcomputerlaptop",
      "description": "zenithsensingcomputerlaptop"
    },
    {
      "@type": "Component",
      "name": "scanningsensingcompassnetwork",
      "schema": "dtmi:com:goldustries:scanningsensingcompassnetwork;3",
      "displayName": "scanningsensingcompassnetwork",
      "description": "scanningsensingcompassnetwork"
    }
  ]
}