{
  "@context": "dtmi:dtdl:context;2",
  "@id": "dtmi:net:turtlesports:zenithsensingcomputerlaptop;29",
  "@type": "Interface",
  "displayName": "Zenithsensingcomputerlaptop",
  "contents": [
    {
      "@type": "Property",
      "name": "acceleration",
      "schema": "time"
    },
    {
      "@type": "Property",
      "name": "tiltAngle",
      "schema": "duration"
    },
    {
      "@type": "Property",
      "name": "temperature",
      "schema": "dateTime"
    },
    {
      "@type": "Property",
      "name": "tiltAngle1",
      "schema": "time"
    },
    {
      "@type": "Property",
      "name": "flowRate",
      "schema": "double"
    },
    {
      "@type": "Command",
      "name": "setBrightness",
      "request": {
        "name": "targetsetBrightness",
        "schema": "integer"
      }
    },
    {
      "@type": "Command",
      "name": "setTemperature",
      "request": {
        "name": "targetsetTemperature",
        "schema": "boolean"
      }
    },
    {
      "@type": "Component",
      "name": "telescopesystemmodule",
      "schema": "dtmi:org:crystalforce:telescopesystemmodule;18",
      "displayName": "telescopesystemmodule",
      "description": "telescopesystemmodule"
    }
  ]
}