{
  "@context": "dtmi:dtdl:context;2",
  "@id": "dtmi:net:quaductions:telescopesystemmodule;20",
  "@type": "Interface",
  "displayName": "Telescopesystemmodule",
  "contents": [
    {
      "@type": "Telemetry",
      "name": "pressure",
      "schema": "integer"
    },
    {
      "@type": "Telemetry",
      "name": "brightness",
      "schema": "double"
    },
    {
      "@type": "Telemetry",
      "name": "brightness1",
      "schema": "double"
    },
    {
      "@type": "Command",
      "name": "setTemperature",
      "request": {
        "name": "targetsetTemperature",
        "schema": "double"
      }
    },
    {
      "@type": "Command",
      "name": "setTiltAngle",
      "request": {
        "name": "targetsetTiltAngle",
        "schema": "double"
      }
    },
    {
      "@type": "Command",
      "name": "setBrightness",
      "request": {
        "name": "targetsetBrightness",
        "schema": "boolean"
      }
    },
    {
      "@type": "Component",
      "name": "sensorynetwork",
      "schema": "dtmi:com:hurricanetworks:sensorynetwork;14",
      "displayName": "sensorynetwork",
      "description": "sensorynetwork"
    },
    {
      "@type": "Component",
      "name": "cyberneticsensormodule",
      "schema": "dtmi:edu:blossomotors:cyberneticsensormodule;25",
      "displayName": "cyberneticsensormodule",
      "description": "cyberneticsensormodule"
    }
  ]
}