{
  "@context": "dtmi:dtdl:context;2",
  "@id": "dtmi:net:quaductions:zenithsensordiagnostician;24",
  "@type": "Interface",
  "displayName": "Zenithsensordiagnostician",
  "contents": [
    {
      "@type": "Telemetry",
      "name": "tiltAngle",
      "schema": "string"
    },
    {
      "@type": "Command",
      "name": "setPressure",
      "request": {
        "name": "targetsetPressure",
        "schema": "long"
      }
    },
    {
      "@type": "Command",
      "name": "setPressure2",
      "request": {
        "name": "targetsetPressure2",
        "schema": "boolean"
      }
    },
    {
      "@type": "Command",
      "name": "setAcceleration",
      "request": {
        "name": "targetsetAcceleration",
        "schema": "boolean"
      }
    },
    {
      "@type": "Command",
      "name": "setTemperature",
      "request": {
        "name": "targetsetTemperature",
        "schema": "long"
      }
    },
    {
      "@type": "Command",
      "name": "setIntensity",
      "request": {
        "name": "targetsetIntensity",
        "schema": "double"
      }
    }
  ]
}