{
  "@context": "dtmi:dtdl:context;2",
  "@id": "dtmi:org:alpite:computerzenithkit;34",
  "@type": "Interface",
  "displayName": "Computerzenithkit",
  "contents": [
    {
      "@type": "Telemetry",
      "name": "pressure",
      "schema": "time"
    },
    {
      "@type": "Telemetry",
      "name": "brightness",
      "schema": "long"
    },
    {
      "@type": "Telemetry",
      "name": "tiltAngle",
      "schema": "long"
    },
    {
      "@type": "Telemetry",
      "name": "brightness1",
      "schema": "date"
    },
    {
      "@type": "Telemetry",
      "name": "temperature",
      "schema": "boolean"
    },
    {
      "@type": "Property",
      "name": "flowRate",
      "schema": "boolean"
    },
    {
      "@type": "Property",
      "name": "pressure1",
      "schema": "float"
    },
    {
      "@type": "Property",
      "name": "brightness2",
      "schema": "duration"
    },
    {
      "@type": "Property",
      "name": "intensity",
      "schema": "date"
    },
    {
      "@type": "Property",
      "name": "pressure2",
      "schema": "integer"
    },
    {
      "@type": "Command",
      "name": "setTiltAngle",
      "request": {
        "name": "targetsetTiltAngle",
        "schema": "integer"
      }
    },
    {
      "@type": "Command",
      "name": "setPressure",
      "request": {
        "name": "targetsetPressure",
        "schema": "dateTime"
      }
    },
    {
      "@type": "Command",
      "name": "setBrightness",
      "request": {
        "name": "targetsetBrightness",
        "schema": "double"
      }
    },
    {
      "@type": "Command",
      "name": "setTemperature",
      "request": {
        "name": "targetsetTemperature",
        "schema": "time"
      }
    },
    {
      "@type": "Component",
      "name": "sensorsensemodule",
      "schema": "dtmi:net:blossomotors:sensorsensemodule;13",
      "displayName": "sensorsensemodule",
      "description": "sensorsensemodule"
    }
  ]
}