{
  "@context": "dtmi:dtdl:context;2",
  "@id": "dtmi:com:microlutions:networkedsystemsensor;20",
  "@type": "Interface",
  "displayName": "Networkedsystemsensor",
  "contents": [
    {
      "@type": "Property",
      "name": "brightness",
      "schema": "long"
    },
    {
      "@type": "Property",
      "name": "intensity",
      "schema": "long"
    },
    {
      "@type": "Property",
      "name": "flowRate",
      "schema": "double"
    },
    {
      "@type": "Command",
      "name": "setAcceleration",
      "request": {
        "name": "targetsetAcceleration",
        "schema": "dateTime"
      }
    },
    {
      "@type": "Command",
      "name": "setTemperature",
      "request": {
        "name": "targetsetTemperature",
        "schema": "float"
      }
    },
    {
      "@type": "Command",
      "name": "setTiltAngle",
      "request": {
        "name": "targetsetTiltAngle",
        "schema": "duration"
      }
    },
    {
      "@type": "Command",
      "name": "setPressure",
      "request": {
        "name": "targetsetPressure",
        "schema": "dateTime"
      }
    },
    {
      "@type": "Command",
      "name": "setAcceleration2",
      "request": {
        "name": "targetsetAcceleration2",
        "schema": "long"
      }
    },
    {
      "@type": "Command",
      "name": "setTemperature2",
      "request": {
        "name": "targetsetTemperature2",
        "schema": "dateTime"
      }
    },
    {
      "@type": "Command",
      "name": "setTemperature3",
      "request": {
        "name": "targetsetTemperature3",
        "schema": "float"
      }
    },
    {
      "@type": "Component",
      "name": "telescopesystemmodule",
      "schema": "dtmi:org:goldustries:telescopesystemmodule;1",
      "displayName": "telescopesystemmodule",
      "description": "telescopesystemmodule"
    }
  ]
}