{
  "@context": "dtmi:dtdl:context;2",
  "@id": "dtmi:gov:blossomotors:computerzenithkit;25",
  "@type": "Interface",
  "displayName": "Computerzenithkit",
  "contents": [
    {
      "@type": "Telemetry",
      "name": "temperature",
      "schema": "duration"
    },
    {
      "@type": "Telemetry",
      "name": "brightness",
      "schema": "long"
    },
    {
      "@type": "Telemetry",
      "name": "tiltAngle",
      "schema": "integer"
    },
    {
      "@type": "Telemetry",
      "name": "brightness1",
      "schema": "duration"
    },
    {
      "@type": "Property",
      "name": "brightness2",
      "schema": "time"
    },
    {
      "@type": "Property",
      "name": "pressure",
      "schema": "date"
    },
    {
      "@type": "Command",
      "name": "setBrightness",
      "request": {
        "name": "targetsetBrightness",
        "schema": "dateTime"
      }
    },
    {
      "@type": "Command",
      "name": "setAcceleration",
      "request": {
        "name": "targetsetAcceleration",
        "schema": "dateTime"
      }
    },
    {
      "@type": "Command",
      "name": "setIntensity",
      "request": {
        "name": "targetsetIntensity",
        "schema": "string"
      }
    },
    {
      "@type": "Command",
      "name": "setBrightness2",
      "request": {
        "name": "targetsetBrightness2",
        "schema": "integer"
      }
    },
    {
      "@type": "Command",
      "name": "setTiltAngle",
      "request": {
        "name": "targetsetTiltAngle",
        "schema": "double"
      }
    },
    {
      "@type": "Command",
      "name": "setTiltAngle2",
      "request": {
        "name": "targetsetTiltAngle2",
        "schema": "time"
      }
    },
    {
      "@type": "Component",
      "name": "compunetworkedsensorscanner",
      "schema": "dtmi:net:accenco:compunetworkedsensorscanner;8",
      "displayName": "compunetworkedsensorscanner",
      "description": "compunetworkedsensorscanner"
    },
    {
      "@type": "Component",
      "name": "zenithsensordiagnostician",
      "schema": "dtmi:com:seedrecords:zenithsensordiagnostician;9",
      "displayName": "zenithsensordiagnostician",
      "description": "zenithsensordiagnostician"
    },
    {
      "@type": "Component",
      "name": "sensingkitmechanism",
      "schema": "dtmi:edu:northstarcorp:sensingkitmechanism;7",
      "displayName": "sensingkitmechanism",
      "description": "sensingkitmechanism"
    }
  ]
}