{
  "@context": "dtmi:dtdl:context;2",
  "@id": "dtmi:gov:blossomotors:zenithsensordiagnostician;19",
  "@type": "Interface",
  "displayName": "Zenithsensordiagnostician",
  "contents": [
    {
      "@type": "Telemetry",
      "name": "acceleration",
      "schema": "float"
    },
    {
      "@type": "Telemetry",
      "name": "pressure",
      "schema": "boolean"
    },
    {
      "@type": "Telemetry",
      "name": "temperature",
      "schema": "double"
    },
    {
      "@type": "Telemetry",
      "name": "brightness",
      "schema": "double"
    },
    {
      "@type": "Property",
      "name": "brightness1",
      "schema": "float"
    },
    {
      "@type": "Property",
      "name": "acceleration1",
      "schema": "long"
    },
    {
      "@type": "Property",
      "name": "brightness2",
      "schema": "dateTime"
    },
    {
      "@type": "Property",
      "name": "tiltAngle",
      "schema": "dateTime"
    },
    {
      "@type": "Component",
      "name": "compunetworkedsensorscanner",
      "schema": "dtmi:gov:shadowhouse:compunetworkedsensorscanner;11",
      "displayName": "compunetworkedsensorscanner",
      "description": "compunetworkedsensorscanner"
    }
  ]
}