{
  "@context": "dtmi:dtdl:context;2",
  "@id": "dtmi:edu:blossomotors:sensorynetwork;27",
  "@type": "Interface",
  "displayName": "Sensorynetwork",
  "contents": [
    {
      "@type": "Telemetry",
      "name": "flowRate",
      "schema": "dateTime"
    },
    {
      "@type": "Telemetry",
      "name": "flowRate1",
      "schema": "duration"
    },
    {
      "@type": "Telemetry",
      "name": "acceleration",
      "schema": "date"
    },
    {
      "@type": "Telemetry",
      "name": "acceleration1",
      "schema": "duration"
    },
    {
      "@type": "Telemetry",
      "name": "brightness",
      "schema": "duration"
    },
    {
      "@type": "Telemetry",
      "name": "temperature",
      "schema": "time"
    },
    {
      "@type": "Property",
      "name": "pressure",
      "schema": "double"
    },
    {
      "@type": "Property",
      "name": "temperature1",
      "schema": "integer"
    },
    {
      "@type": "Property",
      "name": "brightness1",
      "schema": "long"
    },
    {
      "@type": "Property",
      "name": "brightness2",
      "schema": "float"
    },
    {
      "@type": "Property",
      "name": "brightness3",
      "schema": "time"
    },
    {
      "@type": "Property",
      "name": "brightness4",
      "schema": "boolean"
    },
    {
      "@type": "Command",
      "name": "setTiltAngle",
      "request": {
        "name": "targetsetTiltAngle",
        "schema": "double"
      }
    },
    {
      "@type": "Command",
      "name": "setAcceleration",
      "request": {
        "name": "targetsetAcceleration",
        "schema": "long"
      }
    },
    {
      "@type": "Component",
      "name": "locatorprocessor",
      "schema": "dtmi:com:alpite:locatorprocessor;39",
      "displayName": "locatorprocessor",
      "description": "locatorprocessor"
    }
  ]
}