{
  "@context": "dtmi:dtdl:context;2",
  "@id": "dtmi:org:northstarcorp:cyberneticaisensor;23",
  "@type": "Interface",
  "displayName": "Cyberneticaisensor",
  "contents": [
    {
      "@type": "Telemetry",
      "name": "acceleration",
      "schema": "double"
    },
    {
      "@type": "Telemetry",
      "name": "tiltAngle",
      "schema": "dateTime"
    },
    {
      "@type": "Telemetry",
      "name": "tiltAngle1",
      "schema": "boolean"
    },
    {
      "@type": "Telemetry",
      "name": "flowRate",
      "schema": "long"
    },
    {
      "@type": "Telemetry",
      "name": "brightness",
      "schema": "dateTime"
    },
    {
      "@type": "Telemetry",
      "name": "brightness1",
      "schema": "dateTime"
    },
    {
      "@type": "Property",
      "name": "acceleration1",
      "schema": "long"
    },
    {
      "@type": "Command",
      "name": "setIntensity",
      "request": {
        "name": "targetsetIntensity",
        "schema": "boolean"
      }
    },
    {
      "@type": "Command",
      "name": "setAcceleration",
      "request": {
        "name": "targetsetAcceleration",
        "schema": "string"
      }
    },
    {
      "@type": "Command",
      "name": "setPressure",
      "request": {
        "name": "targetsetPressure",
        "schema": "long"
      }
    },
    {
      "@type": "Command",
      "name": "setIntensity2",
      "request": {
        "name": "targetsetIntensity2",
        "schema": "integer"
      }
    },
    {
      "@type": "Command",
      "name": "setIntensity3",
      "request": {
        "name": "targetsetIntensity3",
        "schema": "double"
      }
    },
    {
      "@type": "Command",
      "name": "setPressure2",
      "request": {
        "name": "targetsetPressure2",
        "schema": "dateTime"
      }
    },
    {
      "@type": "Component",
      "name": "telescopesystemmodule",
      "schema": "dtmi:net:ghostnite:telescopesystemmodule;21",
      "displayName": "telescopesystemmodule",
      "description": "telescopesystemmodule"
    },
    {
      "@type": "Component",
      "name": "analyzingsensingcompassunit",
      "schema": "dtmi:com:alpite:analyzingsensingcompassunit;9",
      "displayName": "analyzingsensingcompassunit",
      "description": "analyzingsensingcompassunit"
    }
  ]
}