{
  "@context": "dtmi:dtdl:context;2",
  "@id": "dtmi:gov:northstarcorp:telescopesystemmodule;43",
  "@type": "Interface",
  "displayName": "Telescopesystemmodule",
  "contents": [
    {
      "@type": "Property",
      "name": "brightness",
      "schema": "string"
    },
    {
      "@type": "Property",
      "name": "intensity",
      "schema": "date"
    },
    {
      "@type": "Property",
      "name": "tiltAngle",
      "schema": "long"
    },
    {
      "@type": "Property",
      "name": "temperature",
      "schema": "float"
    },
    {
      "@type": "Property",
      "name": "pressure",
      "schema": "date"
    },
    {
      "@type": "Property",
      "name": "tiltAngle1",
      "schema": "double"
    },
    {
      "@type": "Command",
      "name": "setTemperature",
      "request": {
        "name": "targetsetTemperature",
        "schema": "long"
      }
    },
    {
      "@type": "Command",
      "name": "setAcceleration",
      "request": {
        "name": "targetsetAcceleration",
        "schema": "integer"
      }
    },
    {
      "@type": "Command",
      "name": "setBrightness",
      "request": {
        "name": "targetsetBrightness",
        "schema": "time"
      }
    },
    {
      "@type": "Command",
      "name": "setPressure",
      "request": {
        "name": "targetsetPressure",
        "schema": "boolean"
      }
    },
    {
      "@type": "Command",
      "name": "setTiltAngle",
      "request": {
        "name": "targetsetTiltAngle",
        "schema": "double"
      }
    }
  ]
}