{
  "@context": "dtmi:dtdl:context;2",
  "@id": "dtmi:gov:cliffgold:locatorprocessor;6",
  "@type": "Interface",
  "displayName": "Locatorprocessor",
  "contents": [
    {
      "@type": "Telemetry",
      "name": "tiltAngle",
      "schema": "integer"
    },
    {
      "@type": "Telemetry",
      "name": "intensity",
      "schema": "time"
    },
    {
      "@type": "Telemetry",
      "name": "pressure",
      "schema": "time"
    },
    {
      "@type": "Telemetry",
      "name": "brightness",
      "schema": "boolean"
    },
    {
      "@type": "Telemetry",
      "name": "flowRate",
      "schema": "integer"
    },
    {
      "@type": "Telemetry",
      "name": "acceleration",
      "schema": "dateTime"
    },
    {
      "@type": "Component",
      "name": "compudiagnostic",
      "schema": "dtmi:edu:crystalcoms:compudiagnostic;1",
      "displayName": "compudiagnostic",
      "description": "compudiagnostic"
    }
  ]
}