{
  "@context": "dtmi:dtdl:context;2",
  "@id": "dtmi:net:accenco:compudiagnostic;26",
  "@type": "Interface",
  "displayName": "Compudiagnostic",
  "contents": [
    {
      "@type": "Property",
      "name": "brightness",
      "schema": "long"
    },
    {
      "@type": "Property",
      "name": "tiltAngle",
      "schema": "date"
    },
    {
      "@type": "Property",
      "name": "pressure",
      "schema": "dateTime"
    },
    {
      "@type": "Property",
      "name": "acceleration",
      "schema": "double"
    },
    {
      "@type": "Command",
      "name": "setBrightness",
      "request": {
        "name": "targetsetBrightness",
        "schema": "duration"
      }
    }
  ]
}