{
  "@context": "dtmi:dtdl:context;2",
  "@id": "dtmi:net:accenco:laptopcomputerizedprobepack;47",
  "@type": "Interface",
  "displayName": "Laptopcomputerizedprobepack",
  "contents": [
    {
      "@type": "Telemetry",
      "name": "temperature",
      "schema": "integer"
    },
    {
      "@type": "Property",
      "name": "brightness",
      "schema": "duration"
    },
    {
      "@type": "Property",
      "name": "acceleration",
      "schema": "time"
    },
    {
      "@type": "Property",
      "name": "tiltAngle",
      "schema": "date"
    },
    {
      "@type": "Command",
      "name": "setFlowRate",
      "request": {
        "name": "targetsetFlowRate",
        "schema": "boolean"
      }
    },
    {
      "@type": "Command",
      "name": "setTiltAngle",
      "request": {
        "name": "targetsetTiltAngle",
        "schema": "date"
      }
    },
    {
      "@type": "Command",
      "name": "setBrightness",
      "request": {
        "name": "targetsetBrightness",
        "schema": "float"
      }
    },
    {
      "@type": "Command",
      "name": "setBrightness2",
      "request": {
        "name": "targetsetBrightness2",
        "schema": "dateTime"
      }
    },
    {
      "@type": "Command",
      "name": "setAcceleration",
      "request": {
        "name": "targetsetAcceleration",
        "schema": "float"
      }
    },
    {
      "@type": "Command",
      "name": "setIntensity",
      "request": {
        "name": "targetsetIntensity",
        "schema": "double"
      }
    },
    {
      "@type": "Component",
      "name": "sensorsensemodule",
      "schema": "dtmi:org:shadowhouse:sensorsensemodule;13",
      "displayName": "sensorsensemodule",
      "description": "sensorsensemodule"
    }
  ]
}