{
  "@context": "dtmi:dtdl:context;2",
  "@id": "dtmi:net:accenco:sensornetworkkit;1",
  "@type": "Interface",
  "displayName": "Sensornetworkkit",
  "contents": [
    {
      "@type": "Telemetry",
      "name": "brightness",
      "schema": "float"
    },
    {
      "@type": "Telemetry",
      "name": "temperature",
      "schema": "boolean"
    },
    {
      "@type": "Property",
      "name": "pressure",
      "schema": "date"
    },
    {
      "@type": "Command",
      "name": "setTemperature",
      "request": {
        "name": "targetsetTemperature",
        "schema": "long"
      }
    },
    {
      "@type": "Command",
      "name": "setBrightness",
      "request": {
        "name": "targetsetBrightness",
        "schema": "long"
      }
    },
    {
      "@type": "Command",
      "name": "setTemperature2",
      "request": {
        "name": "targetsetTemperature2",
        "schema": "long"
      }
    },
    {
      "@type": "Command",
      "name": "setTiltAngle",
      "request": {
        "name": "targetsetTiltAngle",
        "schema": "dateTime"
      }
    },
    {
      "@type": "Command",
      "name": "setPressure",
      "request": {
        "name": "targetsetPressure",
        "schema": "date"
      }
    },
    {
      "@type": "Component",
      "name": "analyticaldiagnosticiansystem",
      "schema": "dtmi:com:hurricanetworks:analyticaldiagnosticiansystem;1",
      "displayName": "analyticaldiagnosticiansystem",
      "description": "analyticaldiagnosticiansystem"
    },
    {
      "@type": "Component",
      "name": "analyticaldiagnosticiansystem2",
      "schema": "dtmi:gov:microlutions:analyticaldiagnosticiansystem;2",
      "displayName": "analyticaldiagnosticiansystem2",
      "description": "analyticaldiagnosticiansystem2"
    },
    {
      "@type": "Component",
      "name": "scanningsensingcompassnetwork",
      "schema": "dtmi:edu:seedrecords:scanningsensingcompassnetwork;2",
      "displayName": "scanningsensingcompassnetwork",
      "description": "scanningsensingcompassnetwork"
    }
  ]
}