{
  "@context": "dtmi:dtdl:context;2",
  "@id": "dtmi:net:cliffgold:aicompuunit;13",
  "@type": "Interface",
  "displayName": "Aicompuunit",
  "contents": [
    {
      "@type": "Telemetry",
      "name": "tiltAngle",
      "schema": "boolean"
    },
    {
      "@type": "Property",
      "name": "brightness",
      "schema": "double"
    },
    {
      "@type": "Component",
      "name": "locatorprocessor",
      "schema": "dtmi:com:phantasmentertainment:locatorprocessor;12",
      "displayName": "locatorprocessor",
      "description": "locatorprocessor"
    },
    {
      "@type": "Component",
      "name": "analyzingsystemmechanism",
      "schema": "dtmi:edu:oceanavigations:analyzingsystemmechanism;2",
      "displayName": "analyzingsystemmechanism",
      "description": "analyzingsystemmechanism"
    }
  ]
}