{
  "@context": "dtmi:dtdl:context;2",
  "@id": "dtmi:net:oceanavigations:aisensoryprocessor;32",
  "@type": "Interface",
  "displayName": "Aisensoryprocessor",
  "contents": [
    {
      "@type": "Telemetry",
      "name": "pressure",
      "schema": "integer"
    },
    {
      "@type": "Property",
      "name": "flowRate",
      "schema": "dateTime"
    },
    {
      "@type": "Command",
      "name": "setBrightness",
      "request": {
        "name": "targetsetBrightness",
        "schema": "duration"
      }
    },
    {
      "@type": "Component",
      "name": "laptopcomputerizedprobepack",
      "schema": "dtmi:net:northstarcorp:laptopcomputerizedprobepack;15",
      "displayName": "laptopcomputerizedprobepack",
      "description": "laptopcomputerizedprobepack"
    },
    {
      "@type": "Component",
      "name": "computerzenithkit",
      "schema": "dtmi:com:ghostnite:computerzenithkit;21",
      "displayName": "computerzenithkit",
      "description": "computerzenithkit"
    }
  ]
}