{
  "@context": "dtmi:dtdl:context;2",
  "@id": "dtmi:edu:alpite:locatorprocessor;21",
  "@type": "Interface",
  "displayName": "Locatorprocessor",
  "contents": [
    {
      "@type": "Telemetry",
      "name": "pressure",
      "schema": "float"
    },
    {
      "@type": "Telemetry",
      "name": "intensity",
      "schema": "duration"
    },
    {
      "@type": "Telemetry",
      "name": "flowRate",
      "schema": "string"
    },
    {
      "@type": "Telemetry",
      "name": "tiltAngle",
      "schema": "date"
    },
    {
      "@type": "Command",
      "name": "setPressure",
      "request": {
        "name": "targetsetPressure",
        "schema": "long"
      }
    },
    {
      "@type": "Command",
      "name": "setIntensity",
      "request": {
        "name": "targetsetIntensity",
        "schema": "string"
      }
    },
    {
      "@type": "Command",
      "name": "setPressure2",
      "request": {
        "name": "targetsetPressure2",
        "schema": "string"
      }
    },
    {
      "@type": "Command",
      "name": "setFlowRate",
      "request": {
        "name": "targetsetFlowRate",
        "schema": "float"
      }
    },
    {
      "@type": "Command",
      "name": "setBrightness",
      "request": {
        "name": "targetsetBrightness",
        "schema": "double"
      }
    },
    {
      "@type": "Command",
      "name": "setTiltAngle",
      "request": {
        "name": "targetsetTiltAngle",
        "schema": "boolean"
      }
    },
    {
      "@type": "Component",
      "name": "cyberneticaisensor",
      "schema": "dtmi:edu:oceanavigations:cyberneticaisensor;1",
      "displayName": "cyberneticaisensor",
      "description": "cyberneticaisensor"
    }
  ]
}