{
  "@context": "dtmi:dtdl:context;2",
  "@id": "dtmi:net:crystalforce:analyzingsensingcompassunit;28",
  "@type": "Interface",
  "displayName": "Analyzingsensingcompassunit",
  "contents": [
    {
      "@type": "Telemetry",
      "name": "temperature",
      "schema": "time"
    },
    {
      "@type": "Telemetry",
      "name": "intensity",
      "schema": "string"
    },
    {
      "@type": "Telemetry",
      "name": "pressure",
      "schema": "duration"
    },
    {
      "@type": "Telemetry",
      "name": "acceleration",
      "schema": "boolean"
    },
    {
      "@type": "Telemetry",
      "name": "tiltAngle",
      "schema": "integer"
    },
    {
      "@type": "Command",
      "name": "setAcceleration",
      "request": {
        "name": "targetsetAcceleration",
        "schema": "double"
      }
    },
    {
      "@type": "Command",
      "name": "setTiltAngle",
      "request": {
        "name": "targetsetTiltAngle",
        "schema": "integer"
      }
    },
    {
      "@type": "Command",
      "name": "setBrightness",
      "request": {
        "name": "targetsetBrightness",
        "schema": "duration"
      }
    },
    {
      "@type": "Command",
      "name": "setAcceleration2",
      "request": {
        "name": "targetsetAcceleration2",
        "schema": "double"
      }
    },
    {
      "@type": "Command",
      "name": "setAcceleration3",
      "request": {
        "name": "targetsetAcceleration3",
        "schema": "double"
      }
    },
    {
      "@type": "Component",
      "name": "computerzenithkit",
      "schema": "dtmi:net:oceanavigations:computerzenithkit;9",
      "displayName": "computerzenithkit",
      "description": "computerzenithkit"
    },
    {
      "@type": "Component",
      "name": "sensingkitmechanism",
      "schema": "dtmi:edu:shadowhouse:sensingkitmechanism;18",
      "displayName": "sensingkitmechanism",
      "description": "sensingkitmechanism"
    }
  ]
}