{
  "@context": "dtmi:dtdl:context;2",
  "@id": "dtmi:edu:microlutions:analyzingsystemmechanism;30",
  "@type": "Interface",
  "displayName": "Analyzingsystemmechanism",
  "contents": [
    {
      "@type": "Telemetry",
      "name": "pressure",
      "schema": "double"
    },
    {
      "@type": "Telemetry",
      "name": "brightness",
      "schema": "integer"
    },
    {
      "@type": "Telemetry",
      "name": "brightness1",
      "schema": "duration"
    },
    {
      "@type": "Telemetry",
      "name": "pressure1",
      "schema": "dateTime"
    },
    {
      "@type": "Telemetry",
      "name": "intensity",
      "schema": "duration"
    },
    {
      "@type": "Telemetry",
      "name": "temperature",
      "schema": "boolean"
    },
    {
      "@type": "Property",
      "name": "intensity1",
      "schema": "duration"
    },
    {
      "@type": "Property",
      "name": "intensity2",
      "schema": "duration"
    },
    {
      "@type": "Command",
      "name": "setBrightness",
      "request": {
        "name": "targetsetBrightness",
        "schema": "boolean"
      }
    },
    {
      "@type": "Command",
      "name": "setIntensity",
      "request": {
        "name": "targetsetIntensity",
        "schema": "duration"
      }
    },
    {
      "@type": "Command",
      "name": "setIntensity2",
      "request": {
        "name": "targetsetIntensity2",
        "schema": "float"
      }
    },
    {
      "@type": "Component",
      "name": "cyberneticsensormodule",
      "schema": "dtmi:com:greenlife:cyberneticsensormodule;26",
      "displayName": "cyberneticsensormodule",
      "description": "cyberneticsensormodule"
    },
    {
      "@type": "Component",
      "name": "compunetworkedsensorscanner",
      "schema": "dtmi:org:marsaviation:compunetworkedsensorscanner;15",
      "displayName": "compunetworkedsensorscanner",
      "description": "compunetworkedsensorscanner"
    },
    {
      "@type": "Component",
      "name": "scanningsensingcompassnetwork",
      "schema": "dtmi:com:phantasmentertainment:scanningsensingcompassnetwork;18",
      "displayName": "scanningsensingcompassnetwork",
      "description": "scanningsensingcompassnetwork"
    }
  ]
}