{
  "@context": "dtmi:dtdl:context;2",
  "@id": "dtmi:com:northstarcorp:compunetworkedsensorscanner;21",
  "@type": "Interface",
  "displayName": "Compunetworkedsensorscanner",
  "contents": [
    {
      "@type": "Telemetry",
      "name": "acceleration",
      "schema": "integer"
    },
    {
      "@type": "Telemetry",
      "name": "flowRate",
      "schema": "double"
    },
    {
      "@type": "Telemetry",
      "name": "flowRate1",
      "schema": "integer"
    },
    {
      "@type": "Telemetry",
      "name": "flowRate2",
      "schema": "string"
    },
    {
      "@type": "Property",
      "name": "tiltAngle",
      "schema": "float"
    },
    {
      "@type": "Property",
      "name": "brightness",
      "schema": "double"
    },
    {
      "@type": "Component",
      "name": "locatorprocessor",
      "schema": "dtmi:edu:cliffgold:locatorprocessor;11",
      "displayName": "locatorprocessor",
      "description": "locatorprocessor"
    }
  ]
}