{
  "@context": "dtmi:dtdl:context;2",
  "@id": "dtmi:com:blossomotors:computerzenithkit;12",
  "@type": "Interface",
  "displayName": "Computerzenithkit",
  "contents": [
    {
      "@type": "Telemetry",
      "name": "brightness",
      "schema": "long"
    },
    {
      "@type": "Telemetry",
      "name": "brightness1",
      "schema": "integer"
    },
    {
      "@type": "Telemetry",
      "name": "intensity",
      "schema": "double"
    },
    {
      "@type": "Property",
      "name": "pressure",
      "schema": "string"
    },
    {
      "@type": "Property",
      "name": "temperature",
      "schema": "string"
    },
    {
      "@type": "Property",
      "name": "tiltAngle",
      "schema": "string"
    },
    {
      "@type": "Component",
      "name": "zenithsensingcomputerlaptop",
      "schema": "dtmi:org:greenlife:zenithsensingcomputerlaptop;2",
      "displayName": "zenithsensingcomputerlaptop",
      "description": "zenithsensingcomputerlaptop"
    }
  ]
}