{
  "@context": "dtmi:dtdl:context;2",
  "@id": "dtmi:edu:shadowhouse:aicompuunit;26",
  "@type": "Interface",
  "displayName": "Aicompuunit",
  "contents": [
    {
      "@type": "Telemetry",
      "name": "acceleration",
      "schema": "double"
    },
    {
      "@type": "Telemetry",
      "name": "temperature",
      "schema": "float"
    },
    {
      "@type": "Telemetry",
      "name": "pressure",
      "schema": "double"
    },
    {
      "@type": "Property",
      "name": "intensity",
      "schema": "date"
    },
    {
      "@type": "Property",
      "name": "brightness",
      "schema": "boolean"
    },
    {
      "@type": "Command",
      "name": "setIntensity",
      "request": {
        "name": "targetsetIntensity",
        "schema": "string"
      }
    },
    {
      "@type": "Command",
      "name": "setFlowRate",
      "request": {
        "name": "targetsetFlowRate",
        "schema": "time"
      }
    },
    {
      "@type": "Command",
      "name": "setAcceleration",
      "request": {
        "name": "targetsetAcceleration",
        "schema": "date"
      }
    },
    {
      "@type": "Command",
      "name": "setTiltAngle",
      "request": {
        "name": "targetsetTiltAngle",
        "schema": "date"
      }
    },
    {
      "@type": "Command",
      "name": "setFlowRate2",
      "request": {
        "name": "targetsetFlowRate2",
        "schema": "float"
      }
    }
  ]
}