{
  "@context": "dtmi:dtdl:context;2",
  "@id": "dtmi:org:microlutions:sensorynetwork;23",
  "@type": "Interface",
  "displayName": "Sensorynetwork",
  "contents": [
    {
      "@type": "Telemetry",
      "name": "pressure",
      "schema": "duration"
    },
    {
      "@type": "Telemetry",
      "name": "pressure1",
      "schema": "long"
    },
    {
      "@type": "Property",
      "name": "brightness",
      "schema": "time"
    },
    {
      "@type": "Property",
      "name": "intensity",
      "schema": "boolean"
    },
    {
      "@type": "Property",
      "name": "brightness1",
      "schema": "boolean"
    },
    {
      "@type": "Property",
      "name": "brightness2",
      "schema": "boolean"
    },
    {
      "@type": "Command",
      "name": "setIntensity",
      "request": {
        "name": "targetsetIntensity",
        "schema": "float"
      }
    },
    {
      "@type": "Command",
      "name": "setIntensity2",
      "request": {
        "name": "targetsetIntensity2",
        "schema": "double"
      }
    },
    {
      "@type": "Command",
      "name": "setIntensity3",
      "request": {
        "name": "targetsetIntensity3",
        "schema": "float"
      }
    },
    {
      "@type": "Command",
      "name": "setAcceleration",
      "request": {
        "name": "targetsetAcceleration",
        "schema": "float"
      }
    },
    {
      "@type": "Command",
      "name": "setFlowRate",
      "request": {
        "name": "targetsetFlowRate",
        "schema": "duration"
      }
    },
    {
      "@type": "Component",
      "name": "computerzenithkit",
      "schema": "dtmi:com:quaductions:computerzenithkit;20",
      "displayName": "computerzenithkit",
      "description": "computerzenithkit"
    },
    {
      "@type": "Component",
      "name": "compunetworkedsensorscanner",
      "schema": "dtmi:org:blossomotors:compunetworkedsensorscanner;2",
      "displayName": "compunetworkedsensorscanner",
      "description": "compunetworkedsensorscanner"
    }
  ]
}