{
  "@context": "dtmi:dtdl:context;2",
  "@id": "dtmi:net:blossomotors:networkedsystemsensor;40",
  "@type": "Interface",
  "displayName": "Networkedsystemsensor",
  "contents": [
    {
      "@type": "Property",
      "name": "acceleration",
      "schema": "double"
    },
    {
      "@type": "Property",
      "name": "brightness",
      "schema": "time"
    },
    {
      "@type": "Property",
      "name": "brightness1",
      "schema": "boolean"
    },
    {
      "@type": "Property",
      "name": "acceleration1",
      "schema": "dateTime"
    },
    {
      "@type": "Property",
      "name": "temperature",
      "schema": "date"
    },
    {
      "@type": "Property",
      "name": "pressure",
      "schema": "double"
    },
    {
      "@type": "Command",
      "name": "setPressure",
      "request": {
        "name": "targetsetPressure",
        "schema": "integer"
      }
    },
    {
      "@type": "Command",
      "name": "setBrightness",
      "request": {
        "name": "targetsetBrightness",
        "schema": "double"
      }
    },
    {
      "@type": "Command",
      "name": "setIntensity",
      "request": {
        "name": "targetsetIntensity",
        "schema": "integer"
      }
    },
    {
      "@type": "Command",
      "name": "setIntensity2",
      "request": {
        "name": "targetsetIntensity2",
        "schema": "long"
      }
    },
    {
      "@type": "Component",
      "name": "sensingkitmechanism",
      "schema": "dtmi:org:northstarcorp:sensingkitmechanism;16",
      "displayName": "sensingkitmechanism",
      "description": "sensingkitmechanism"
    }
  ]
}