{
  "@context": "dtmi:dtdl:context;2",
  "@id": "dtmi:org:quaductions:scanningsensingcompassnetwork;10",
  "@type": "Interface",
  "displayName": "Scanningsensingcompassnetwork",
  "contents": [
    {
      "@type": "Command",
      "name": "setIntensity",
      "request": {
        "name": "targetsetIntensity",
        "schema": "long"
      }
    },
    {
      "@type": "Command",
      "name": "setAcceleration",
      "request": {
        "name": "targetsetAcceleration",
        "schema": "integer"
      }
    },
    {
      "@type": "Command",
      "name": "setPressure",
      "request": {
        "name": "targetsetPressure",
        "schema": "time"
      }
    },
    {
      "@type": "Component",
      "name": "zenithsensordiagnostician",
      "schema": "dtmi:edu:crystalcoms:zenithsensordiagnostician;10",
      "displayName": "zenithsensordiagnostician",
      "description": "zenithsensordiagnostician"
    },
    {
      "@type": "Component",
      "name": "locatorprocessor",
      "schema": "dtmi:com:cliffgold:locatorprocessor;2",
      "displayName": "locatorprocessor",
      "description": "locatorprocessor"
    }
  ]
}