{
  "@context": "dtmi:dtdl:context;2",
  "@id": "dtmi:com:hurricanetworks:sensornetworkkit;33",
  "@type": "Interface",
  "displayName": "Sensornetworkkit",
  "contents": [
    {
      "@type": "Command",
      "name": "setIntensity",
      "request": {
        "name": "targetsetIntensity",
        "schema": "time"
      }
    },
    {
      "@type": "Component",
      "name": "aisensoryprocessor",
      "schema": "dtmi:com:greenlife:aisensoryprocessor;22",
      "displayName": "aisensoryprocessor",
      "description": "aisensoryprocessor"
    }
  ]
}