{
  "@context": "dtmi:dtdl:context;2",
  "@id": "dtmi:net:crystalcoms:sensornetworkkit;20",
  "@type": "Interface",
  "displayName": "Sensornetworkkit",
  "contents": [
    {
      "@type": "Telemetry",
      "name": "flowRate",
      "schema": "duration"
    },
    {
      "@type": "Telemetry",
      "name": "temperature",
      "schema": "time"
    },
    {
      "@type": "Telemetry",
      "name": "acceleration",
      "schema": "double"
    },
    {
      "@type": "Telemetry",
      "name": "pressure",
      "schema": "duration"
    },
    {
      "@type": "Telemetry",
      "name": "tiltAngle",
      "schema": "boolean"
    },
    {
      "@type": "Telemetry",
      "name": "flowRate1",
      "schema": "dateTime"
    },
    {
      "@type": "Property",
      "name": "brightness",
      "schema": "time"
    },
    {
      "@type": "Property",
      "name": "intensity",
      "schema": "double"
    },
    {
      "@type": "Property",
      "name": "acceleration1",
      "schema": "date"
    },
    {
      "@type": "Command",
      "name": "setBrightness",
      "request": {
        "name": "targetsetBrightness",
        "schema": "string"
      }
    },
    {
      "@type": "Command",
      "name": "setTemperature",
      "request": {
        "name": "targetsetTemperature",
        "schema": "duration"
      }
    },
    {
      "@type": "Command",
      "name": "setFlowRate",
      "request": {
        "name": "targetsetFlowRate",
        "schema": "float"
      }
    },
    {
      "@type": "Command",
      "name": "setTemperature2",
      "request": {
        "name": "targetsetTemperature2",
        "schema": "time"
      }
    },
    {
      "@type": "Component",
      "name": "analyzingsensingcompassunit",
      "schema": "dtmi:gov:alpite:analyzingsensingcompassunit;1",
      "displayName": "analyzingsensingcompassunit",
      "description": "analyzingsensingcompassunit"
    },
    {
      "@type": "Component",
      "name": "sensorsensemodule",
      "schema": "dtmi:gov:shadowhouse:sensorsensemodule;5",
      "displayName": "sensorsensemodule",
      "description": "sensorsensemodule"
    }
  ]
}