{
  "@context": "dtmi:dtdl:context;2",
  "@id": "dtmi:net:hurricanetworks:sensorynetwork;17",
  "@type": "Interface",
  "displayName": "Sensorynetwork",
  "contents": [
    {
      "@type": "Telemetry",
      "name": "tiltAngle",
      "schema": "boolean"
    },
    {
      "@type": "Telemetry",
      "name": "tiltAngle1",
      "schema": "date"
    },
    {
      "@type": "Telemetry",
      "name": "pressure",
      "schema": "boolean"
    },
    {
      "@type": "Telemetry",
      "name": "brightness",
      "schema": "string"
    },
    {
      "@type": "Telemetry",
      "name": "brightness1",
      "schema": "double"
    },
    {
      "@type": "Telemetry",
      "name": "acceleration",
      "schema": "boolean"
    },
    {
      "@type": "Command",
      "name": "setBrightness",
      "request": {
        "name": "targetsetBrightness",
        "schema": "dateTime"
      }
    },
    {
      "@type": "Command",
      "name": "setIntensity",
      "request": {
        "name": "targetsetIntensity",
        "schema": "date"
      }
    },
    {
      "@type": "Component",
      "name": "laptopcomputerizedprobepack",
      "schema": "dtmi:com:crystalforce:laptopcomputerizedprobepack;6",
      "displayName": "laptopcomputerizedprobepack",
      "description": "laptopcomputerizedprobepack"
    }
  ]
}