{
  "@context": "dtmi:dtdl:context;2",
  "@id": "dtmi:org:oceanavigations:analyzingsystemmechanism;4",
  "@type": "Interface",
  "displayName": "Analyzingsystemmechanism",
  "contents": [
    {
      "@type": "Telemetry",
      "name": "tiltAngle",
      "schema": "string"
    },
    {
      "@type": "Telemetry",
      "name": "brightness",
      "schema": "duration"
    },
    {
      "@type": "Telemetry",
      "name": "pressure",
      "schema": "boolean"
    },
    {
      "@type": "Telemetry",
      "name": "tiltAngle1",
      "schema": "dateTime"
    },
    {
      "@type": "Property",
      "name": "pressure1",
      "schema": "integer"
    },
    {
      "@type": "Property",
      "name": "flowRate",
      "schema": "float"
    },
    {
      "@type": "Property",
      "name": "tiltAngle2",
      "schema": "double"
    },
    {
      "@type": "Property",
      "name": "brightness1",
      "schema": "boolean"
    },
    {
      "@type": "Component",
      "name": "zenithsensingcomputerlaptop",
      "schema": "dtmi:gov:crystalforce:zenithsensingcomputerlaptop;2",
      "displayName": "zenithsensingcomputerlaptop",
      "description": "zenithsensingcomputerlaptop"
    }
  ]
}