{
  "@context": "dtmi:dtdl:context;2",
  "@id": "dtmi:gov:goldustries:compudiagnostic;11",
  "@type": "Interface",
  "displayName": "Compudiagnostic",
  "contents": [
    {
      "@type": "Telemetry",
      "name": "brightness",
      "schema": "time"
    },
    {
      "@type": "Telemetry",
      "name": "pressure",
      "schema": "time"
    },
    {
      "@type": "Telemetry",
      "name": "tiltAngle",
      "schema": "float"
    },
    {
      "@type": "Telemetry",
      "name": "flowRate",
      "schema": "date"
    },
    {
      "@type": "Telemetry",
      "name": "brightness1",
      "schema": "boolean"
    },
    {
      "@type": "Component",
      "name": "compudiagnostic",
      "schema": "dtmi:com:crystalcoms:compudiagnostic;4",
      "displayName": "compudiagnostic",
      "description": "compudiagnostic"
    },
    {
      "@type": "Component",
      "name": "computerzenithkit",
      "schema": "dtmi:edu:alpite:computerzenithkit;7",
      "displayName": "computerzenithkit",
      "description": "computerzenithkit"
    }
  ]
}