{
  "@context": "dtmi:dtdl:context;2",
  "@id": "dtmi:gov:goldustries:telescopesystemmodule;23",
  "@type": "Interface",
  "displayName": "Telescopesystemmodule",
  "contents": [
    {
      "@type": "Telemetry",
      "name": "flowRate",
      "schema": "integer"
    },
    {
      "@type": "Property",
      "name": "temperature",
      "schema": "float"
    },
    {
      "@type": "Property",
      "name": "acceleration",
      "schema": "duration"
    },
    {
      "@type": "Property",
      "name": "acceleration1",
      "schema": "time"
    },
    {
      "@type": "Command",
      "name": "setAcceleration",
      "request": {
        "name": "targetsetAcceleration",
        "schema": "string"
      }
    },
    {
      "@type": "Command",
      "name": "setTiltAngle",
      "request": {
        "name": "targetsetTiltAngle",
        "schema": "boolean"
      }
    },
    {
      "@type": "Command",
      "name": "setBrightness",
      "request": {
        "name": "targetsetBrightness",
        "schema": "time"
      }
    }
  ]
}