{
  "@context": "dtmi:dtdl:context;2",
  "@id": "dtmi:org:blossomotors:cyberneticaisensor;27",
  "@type": "Interface",
  "displayName": "Cyberneticaisensor",
  "contents": [
    {
      "@type": "Telemetry",
      "name": "brightness",
      "schema": "duration"
    },
    {
      "@type": "Property",
      "name": "brightness1",
      "schema": "float"
    },
    {
      "@type": "Command",
      "name": "setPressure",
      "request": {
        "name": "targetsetPressure",
        "schema": "string"
      }
    },
    {
      "@type": "Command",
      "name": "setBrightness",
      "request": {
        "name": "targetsetBrightness",
        "schema": "dateTime"
      }
    },
    {
      "@type": "Component",
      "name": "scanningcomputersensor",
      "schema": "dtmi:edu:greenlife:scanningcomputersensor;26",
      "displayName": "scanningcomputersensor",
      "description": "scanningcomputersensor"
    }
  ]
}